[
	{
		"__TYPE__": "SharedSliceContent",
		"variation": "default",
		"primary": {
			"title": {
				"__TYPE__": "StructuredTextContent",
				"value": [
					{
						"type": "paragraph",
						"content": {
							"text": "Occaecat culpa consectetur laboris et consequat. Consectetur aliquip eiusmod ex in ex consectetur sint ex cupidatat qui cillum incididunt labore nostrud."
						}
					}
				]
			},
			"subtitle": {
				"__TYPE__": "FieldContent",
				"value": "vote",
				"type": "Text"
			},
			"groupempieza": {
				"__TYPE__": "GroupContentType",
				"value": [
					{
						"__TYPE__": "GroupItemContent",
						"value": [
							[
								"linkbutton",
								{
									"__TYPE__": "LinkContent",
									"value": {
										"__TYPE__": "ExternalLink",
										"url": "https://prismic.io"
									}
								}
							],
							[
								"labelbutton",
								{
									"__TYPE__": "FieldContent",
									"value": "onto",
									"type": "Text"
								}
							]
						]
					}
				]
			}
		},
		"items": []
	}
]